PrecipitationProperties.py
SnowModelVariables.py
SnowpackVariables.py
__init__.py
calcAlbedo.py
calcDewpoint.py
calcEnergyToCC.py
calcEnergyToMelt.py
calcEnergyToRefreezing.py
calcFreshSnowDensity.py
calcInclinationAngle.py
calcLatHeatSub.py
calcLatHeatVap.py
calcLongwave.py
calcPhase.py
calcRH.py
calcSnowDensity.py
calcSnowDensityAfterSnow.py
calcSpecificHumidity.py
calcSublimation.py
calcTurbulentFluxes.py
constants.py
conversion.py
createParameterFile.py
matlab_load.py
runsnowclim_model.py
snowclim_model.py
to_daily_means.py
updatePackWater.py
pysnowclim-0.1.0.dist-info/LICENSE
pysnowclim-0.1.0.dist-info/METADATA
pysnowclim-0.1.0.dist-info/WHEEL
pysnowclim-0.1.0.dist-info/top_level.txt
pysnowclim-0.1.0.dist-info/RECORD
