Metadata-Version: 2.1
Name: pysnowclim
Version: 0.1.0
Summary: A standalone package for the pySnowclim hydrological module.
Author: Abby, Aranildo, Raj
Project-URL: Homepage, https://github.com/abbylute/pySnowClim
Project-URL: Repository, https://github.com/abbylute/pySnowClim
Project-URL: Issues, https://github.com/abbylute/pySnowClim/issues
Requires-Python: >=3.8
License-File: LICENSE
Requires-Dist: numpy>=1.19.0
Requires-Dist: xarray>=0.18.0
Requires-Dist: scipy>=1.6.0
Requires-Dist: netCDF4>=1.5.0
Requires-Dist: pandas>=1.2.0
Requires-Dist: requests>=2.25.0
Requires-Dist: matplotlib>=3.3.0
Provides-Extra: dev
Requires-Dist: pytest>=6.0; extra == "dev"
Requires-Dist: black>=21.0; extra == "dev"
Requires-Dist: mypy>=0.900; extra == "dev"
Requires-Dist: pytest-cov>=2.12.0; extra == "dev"
